confit/__init__.py
confit/cli.py
confit/config.py
confit/draft.py
confit/errors.py
confit/registry.py
confit/typing.py
confit/utils/__init__.py
confit/utils/collections.py
confit/utils/eval.py
confit/utils/random.py
confit/utils/settings.py
confit/utils/xjson.py
confit-0.10.2.dist-info/licenses/LICENSE
confit-0.10.2.dist-info/METADATA
confit-0.10.2.dist-info/WHEEL
confit-0.10.2.dist-info/top_level.txt
confit-0.10.2.dist-info/RECORD
