Metadata-Version: 2.4
Name: confit
Version: 0.10.2
Summary: Smart configuration framework
Author-email: Perceval Wajsburt <perceval.wajsburt@aphp.fr>, Thomas Petit-Jean <thomas.petitjean@aphp.fr>, Adam Remaki <adam.remaki@aphp.fr>, Alice Calliger <alice.calliger@aphp.fr>
License: Copyright 2023 Assistance Publique - Hôpitaux de Paris
Requires-Python: <4.0,>=3.7.1
License-File: LICENSE
Requires-Dist: catalogue<3.0,>=2.0.7
Requires-Dist: lark<2.0,>=1.1.5
Requires-Dist: pydantic<3.0,>=1.2
Requires-Dist: typer<1.0,>=0.6.1
Requires-Dist: pydantic-core>=0.20
Requires-Dist: PyYAML
Requires-Dist: click<8.2
Dynamic: license-file
